{
  "name": "noisy-room",
  "description": "Single 720 Hz source at (1.5, 1.2) plus broadband room noise (noiseAmplitude = 0.05). Matches SimulationScenarios.noisyRoom().",
  "room": {
    "widthMeters": 3.0,
    "heightMeters": 2.0,
    "reflectionGain": 0.0,
    "noiseAmplitude": 0.05
  },
  "array": {
    "sampleRateHz": 16000,
    "microphones": [
      { "id": "m0", "channel": 0, "position": [1.35, 0.0] },
      { "id": "m1", "channel": 1, "position": [1.65, 0.0] },
      { "id": "m2", "channel": 2, "position": [1.35, 0.3] },
      { "id": "m3", "channel": 3, "position": [1.65, 0.3] }
    ]
  },
  "emitters": [
    {
      "id": "e0",
      "position": [1.5, 1.2],
      "velocity": [0.0, 0.0],
      "frequencyHz": 720.0,
      "amplitude": 0.5
    }
  ],
  "durationSeconds": 0.5,
  "randomSeed": 3,
  "groundTruth": {
    "trajectory": "linear",
    "expectedTrackCount": 1
  }
}
